Metadata-Version: 2.2
Name: pyxx
Version: 1.1.0
Summary: Collection of utilities for Python code
Home-page: https://github.com/nathan-hess/python-utilities
Author: Nathan Hess
License: MPL-2.0
Project-URL: Documentation, https://pyxx.readthedocs.io
Requires-Python: >=3.8
License-File: LICENSE
Requires-Dist: numpy
Requires-Dist: sympy
